_graphillion.cpython-312-darwin.so
graphillion/__init__.py
graphillion/digraphset.py
graphillion/edgevertex_setset.py
graphillion/graphclass.py
graphillion/graphset.py
graphillion/release.py
graphillion/setset.py
graphillion/setset_base.py
graphillion/tutorial.py
graphillion/universe.py
graphillion/vertex_setset.py
graphillion/test/__init__.py
graphillion/test/digraphset.py
graphillion/test/edgevertex_setset.py
graphillion/test/graphclass.py
graphillion/test/graphset.py
graphillion/test/setset.py
graphillion/test/tutorial.py
graphillion/test/vertex_setset.py
graphillion-2.1.dist-info/licenses/LICENSE.txt
graphillion-2.1.dist-info/METADATA
graphillion-2.1.dist-info/WHEEL
graphillion-2.1.dist-info/top_level.txt
graphillion-2.1.dist-info/RECORD
