Metadata-Version: 2.4
Name: graphillion
Version: 2.1
Summary: Fast, lightweight library for a huge number of graphs
Home-page: http://graphillion.org/
Author: Hiroki Yamazaki, Takeshi Konishi
Author-email: Takeru Inoue <takeru.inoue@gmail.com>, Hiroaki Iwashita <iwashita@erato.ist.hokudai.ac.jp>, Jun Kawahara <jkawahara@i.kyoto-u.ac.jp>, Shin-ichi Minato <minato@i.kyoto-u.ac.jp>
License: MIT License
Project-URL: Homepage, http://graphillion.org/
Keywords: graph,set,math,network
Classifier: Development Status :: 4 - Beta
Classifier: Intended Audience :: Developers
Classifier: Intended Audience :: Science/Research
Classifier: Operating System :: POSIX :: Linux
Classifier: Operating System :: POSIX :: BSD :: FreeBSD
Classifier: Operating System :: MacOS :: MacOS X
Classifier: Programming Language :: C
Classifier: Programming Language :: C++
Classifier: Programming Language :: Python :: 3.6
Classifier: Programming Language :: Python :: 3.7
Classifier: Programming Language :: Python :: 3.8
Classifier: Programming Language :: Python :: 3.9
Classifier: Programming Language :: Python :: 3.10
Classifier: Programming Language :: Python :: 3.11
Classifier: Programming Language :: Python :: 3
Classifier: Topic :: Software Development :: Libraries :: Python Modules
Classifier: Topic :: Scientific/Engineering :: Information Analysis
Classifier: Topic :: Scientific/Engineering :: Mathematics
License-File: LICENSE.txt
Dynamic: home-page
Dynamic: license-file
